{
  "success": "true",
  "code": "20000",
  "message": "통신 성공",
  "data": {
    "user_id": "56",
    "name": "전하윤",
    "email": "user56@poticard.com",
    "url": "github.com/user56",
    "affiliation": "UI/UX Designer",
    "namecard_title": "전하윤입니다. UI/UX Designer로 일하고 있습니다.",
    "phone": "010-1234-5678",
    "address": "Seoul, Korea",
    "gender": "F",
    "keywords": [
      "TypeScript",
      "Kubernetes",
      "Python",
      "AWS"
    ],
    "style": {
      "color": "red",
      "typoFont": "Sans-serif",
      "cardTexture": "Plastic",
      "logo": "true",
      "qrcode": "true",
      "avatar": "https://api.dicebear.com/7.x/open-peeps/svg?seed=tolyc"
    }
  }
}